setup.py
tornetcd/__init__.py
tornetcd/client.py
tornetcd/etcd_result.py
tornetcd/exceptions.py
tornetcd.egg-info/PKG-INFO
tornetcd.egg-info/SOURCES.txt
tornetcd.egg-info/dependency_links.txt
tornetcd.egg-info/requires.txt
tornetcd.egg-info/top_level.txt
tornetcd/tests/__init__.py
tornetcd/tests/run.py
tornetcd/tests/test_delete.py
tornetcd/tests/test_exception.py
tornetcd/tests/test_get.py
tornetcd/tests/test_search_machine.py
tornetcd/tests/test_status.py
tornetcd/tests/test_write_read.py