Metadata-Version: 1.1
Name: tornetcd
Version: 0.1.0
Summary: async etcd(python-etcd) client for tornado
Home-page: https://github.com/mqingyn/tornetcd
Author: mqingyn
Author-email: mqingyn@gmail.com
License: BSD
Keywords: python etcd async tornado
Platform: UNKNOWN
Classifier: Development Status :: 4 - Beta
Classifier: License :: OSI Approved :: BSD License
Classifier: Programming Language :: Python :: 2
Classifier: Programming Language :: Python :: 2.6
Classifier: Programming Language :: Python :: 2.7
Classifier: Programming Language :: Python :: Implementation :: CPython
Classifier: Programming Language :: Python :: Implementation :: PyPy
Requires: tornado
